{
  "name": "Dominik Kowalczyk",
  "age": 12,
  "gender": "male",
  "location": "Flat 2 Osier Grove Estate, Dalston, London",
  "occupation": "student",
  "industry": "Student",
  "education": "Secondary school",
  "political_lean": "Too young for political preference",
  "personality_sketch": "Dominik is an enthusiastic and curious boy who loves playing football and video games. He is particularly interested in science and frequently experiments with small projects at home. Dominik is outgoing and makes friends easily at school."
}